test_tscai_1/__init__.py
test_tscai_1/classifiers.py
test_tscai_1/constants.py
test_tscai_1/dataloaders.py
test_tscai_1/utils.py
test_tscai_1/models/__init__.py
test_tscai_1/models/cnn.py
test_tscai_1/models/fcn.py
test_tscai_1/models/inception.py
test_tscai_1/models/mlp.py
test_tscai_1/models/resnet.py
test_tscai_1-0.0.32.dist-info/METADATA
test_tscai_1-0.0.32.dist-info/WHEEL
test_tscai_1-0.0.32.dist-info/top_level.txt
test_tscai_1-0.0.32.dist-info/RECORD
