Metadata-Version: 2.1
Name: test-tscai-1
Version: 0.0.32
Summary: Time series classification using Deep Learning
Author: JavidanAbdullayev (Javidan Abdullayev)
Author-email: <javidan.abdullayev@uha.fr>
Classifier: Development Status :: 1 - Planning
Classifier: Intended Audience :: Developers
Classifier: Programming Language :: Python :: 3
Classifier: Operating System :: Unix
Classifier: Operating System :: MacOS :: MacOS X
Classifier: Operating System :: Microsoft :: Windows
Requires-Dist: numpy
Requires-Dist: pandas
Requires-Dist: sklearn
Requires-Dist: importlib
Requires-Dist: torch
Requires-Dist: torchsummary
Requires-Dist: test-datasets-1
